flake8_jira_todo_checker/__init__.py
flake8_jira_todo_checker/checker.py
flake8_jira_todo_checker/jira_client.py
flake8_jira_todo_checker/version.py
flake8_jira_todo_checker-0.6.1.dist-info/entry_points.txt
flake8_jira_todo_checker-0.6.1.dist-info/LICENSE
flake8_jira_todo_checker-0.6.1.dist-info/WHEEL
flake8_jira_todo_checker-0.6.1.dist-info/METADATA
flake8_jira_todo_checker-0.6.1.dist-info/RECORD
